cucumber_compatibility_kit/__init__.py
cucumber_compatibility_kit/compatibility_kit.py
cucumber_compatibility_kit/features/.gitignore
cucumber_compatibility_kit/features/all-statuses/all-statuses.feature
cucumber_compatibility_kit/features/all-statuses/all-statuses.ndjson
cucumber_compatibility_kit/features/ambiguous/ambiguous.feature
cucumber_compatibility_kit/features/ambiguous/ambiguous.ndjson
cucumber_compatibility_kit/features/attachments/attachments.feature
cucumber_compatibility_kit/features/attachments/attachments.ndjson
cucumber_compatibility_kit/features/attachments/cucumber.jpeg
cucumber_compatibility_kit/features/attachments/cucumber.png
cucumber_compatibility_kit/features/attachments/document.pdf
cucumber_compatibility_kit/features/backgrounds/backgrounds.feature
cucumber_compatibility_kit/features/backgrounds/backgrounds.ndjson
cucumber_compatibility_kit/features/cdata/cdata.feature
cucumber_compatibility_kit/features/cdata/cdata.ndjson
cucumber_compatibility_kit/features/data-tables/data-tables.feature
cucumber_compatibility_kit/features/data-tables/data-tables.ndjson
cucumber_compatibility_kit/features/doc-strings/doc-strings.feature
cucumber_compatibility_kit/features/doc-strings/doc-strings.ndjson
cucumber_compatibility_kit/features/empty/empty.feature
cucumber_compatibility_kit/features/empty/empty.ndjson
cucumber_compatibility_kit/features/examples-tables/examples-tables.feature
cucumber_compatibility_kit/features/examples-tables/examples-tables.ndjson
cucumber_compatibility_kit/features/examples-tables-attachment/cucumber.jpeg
cucumber_compatibility_kit/features/examples-tables-attachment/cucumber.png
cucumber_compatibility_kit/features/examples-tables-attachment/examples-tables-attachment.feature
cucumber_compatibility_kit/features/examples-tables-attachment/examples-tables-attachment.ndjson
cucumber_compatibility_kit/features/examples-tables-undefined/examples-tables-undefined.ndjson
cucumber_compatibility_kit-28.0.1.dist-info/licenses/LICENSE
cucumber_compatibility_kit-28.0.1.dist-info/WHEEL
cucumber_compatibility_kit-28.0.1.dist-info/METADATA
cucumber_compatibility_kit-28.0.1.dist-info/RECORD
