Metadata-Version: 2.4
Name: cucumber-compatibility-kit
Version: 28.0.1
Summary: Test data used to validate a Cucumber implementation
Keywords: BDD,testing,cucumber,compatibility,kit
Author: Jason Allen
Author-email: Jason Allen <jsa34@noreply.github.com>
License-Expression: MIT
License-File: LICENSE
Classifier: Development Status :: 3 - Alpha
Classifier: Intended Audience :: Developers
Classifier: Operating System :: OS Independent
Classifier: Programming Language :: Python :: 3
Classifier: Programming Language :: Python :: 3.10
Classifier: Programming Language :: Python :: 3.11
Classifier: Programming Language :: Python :: 3.12
Classifier: Programming Language :: Python :: 3.13
Classifier: Programming Language :: Python :: 3.14
Classifier: Programming Language :: Python :: Implementation :: CPython
Classifier: Programming Language :: Python :: Implementation :: PyPy
Classifier: Topic :: Software Development :: Testing
Classifier: Topic :: Software Development :: Libraries :: Python Modules
Classifier: Topic :: Utilities
Classifier: License :: OSI Approved :: MIT License
Requires-Python: >=3.10
Project-URL: Homepage, https://github.com/cucumber/compatibility-kit
Project-URL: Repository, https://github.com/cucumber/compatibility-kit.git
Project-URL: Download, https://pypi.python.org/pypi/compatibility-kit
Project-URL: Issues, https://github.com/cucumber/compatibility-kit/issues
Project-URL: Changelog, https://github.com/cucumber/compatibility-kit/releases
